qt5_tools/__init__.py
qt5_tools/_version.py
qt5_tools/entrypoints.py
qt5_tools/tests/__init__.py
qt5_tools/tests/test_entrypoints.py
qt5_tools-5.15.1.1.1.dist-info/COPYING
qt5_tools-5.15.1.1.1.dist-info/METADATA
qt5_tools-5.15.1.1.1.dist-info/WHEEL
qt5_tools-5.15.1.1.1.dist-info/entry_points.txt
qt5_tools-5.15.1.1.1.dist-info/top_level.txt
qt5_tools-5.15.1.1.1.dist-info/RECORD
